pybooru/__init__.py
pybooru/api_danbooru.py
pybooru/api_moebooru.py
pybooru/danbooru.py
pybooru/exceptions.py
pybooru/moebooru.py
pybooru/pybooru.py
pybooru/resources.py
Pybooru-4.2.2.dist-info/LICENSE
Pybooru-4.2.2.dist-info/METADATA
Pybooru-4.2.2.dist-info/WHEEL
Pybooru-4.2.2.dist-info/top_level.txt
Pybooru-4.2.2.dist-info/RECORD
