Metadata-Version: 2.1
Name: Pybooru
Version: 4.2.2
Summary: Pybooru is a Python package to access to the API of Danbooru/Moebooru based sites.
Home-page: https://github.com/LuqueDaniel/pybooru
Author: Daniel Luque <danielluque14[at]gmail[dot]com>
Author-email: danielluque14@gmail.com
License: MIT License
Keywords: Pybooru moebooru danbooru API client
Platform: any
Classifier: Development Status :: 5 - Production/Stable
Classifier: Programming Language :: Python
Classifier: Programming Language :: Python :: 2.7
Classifier: Programming Language :: Python :: 3
Classifier: Programming Language :: Python :: 3.5
Classifier: Programming Language :: Python :: 3.6
Classifier: Programming Language :: Python :: 3.7
Classifier: Programming Language :: Python :: 3.8
Classifier: Intended Audience :: Developers
Classifier: License :: OSI Approved :: MIT License
Classifier: Topic :: Documentation :: Sphinx
Classifier: Topic :: Software Development :: Libraries :: Python Modules
Classifier: Topic :: Internet
